src/djangoeasyauth/__init__.py
src/djangoeasyauth/models.py
src/djangoeasyauth/renderers.py
src/djangoeasyauth/serializers.py
src/djangoeasyauth/utils.py
src/djangoeasyauth/views.py
ss_djangoeasyauth-0.0.1.dist-info/METADATA
ss_djangoeasyauth-0.0.1.dist-info/WHEEL
ss_djangoeasyauth-0.0.1.dist-info/licenses/LICENSE
ss_djangoeasyauth-0.0.1.dist-info/RECORD
