Metadata-Version: 2.1
Name: ss-djangoeasyauth
Version: 0.0.1
Summary: A premade django package for authentication with JWT
Author-email: Claudio Lavacca <lavacca.c@gmail.com>
License-File: LICENSE
Classifier: License :: OSI Approved :: MIT License
Classifier: Operating System :: OS Independent
Classifier: Programming Language :: Python :: 3
Requires-Python: >=3.7
Requires-Dist: django
Requires-Dist: djangorestframework
Requires-Dist: djangorestframework-simplejwt
